awsalot/__init__.py
awsalot/rds_sg_connector.py
awsalot/secret_to_pgconn.py
awsalot-0.0.6.dist-info/METADATA
awsalot-0.0.6.dist-info/WHEEL
awsalot-0.0.6.dist-info/entry_points.txt
awsalot-0.0.6.dist-info/top_level.txt
awsalot-0.0.6.dist-info/RECORD
