Metadata-Version: 2.1
Name: awsalot
Version: 0.0.6
Summary: A collection of CLI utils for helping with AWS tasks
Author-email: Anthony Lukach <anthonylukach@gmail.com>
License: MIT License
Requires-Dist: click
Requires-Dist: inquirer
Requires-Dist: boto3
